weacceptpayments/__init__.py
weacceptpayments/consts.py
weacceptpayments/decorators.py
weacceptpayments/exceptions.py
weacceptpayments/misc.py
weacceptpayments/mixins.py
weacceptpayments/testing.py
weacceptpayments/weaccept.py
weacceptpayments-2.4.dist-info/LICENSE
weacceptpayments-2.4.dist-info/METADATA
weacceptpayments-2.4.dist-info/WHEEL
weacceptpayments-2.4.dist-info/top_level.txt
weacceptpayments-2.4.dist-info/RECORD
