Metadata-Version: 2.1
Name: weacceptpayments
Version: 2.4
Summary: Make payments using weaccept.co API and Python.
Home-page: https://github.com/LeOndaz/WeAcceptPayments
Author: Ahmed I.Elsayed
Author-email: ahmeddark369@gmail.com
License: UNKNOWN
Platform: UNKNOWN
Classifier: Programming Language :: Python :: 3
Classifier: License :: OSI Approved :: MIT License
Classifier: Operating System :: OS Independent
Requires-Python: >=3.4
